mechanism/__init__.py
zen_mechanizm-1.0.1.dist-info/METADATA
zen_mechanizm-1.0.1.dist-info/WHEEL
zen_mechanizm-1.0.1.dist-info/top_level.txt
zen_mechanizm-1.0.1.dist-info/RECORD
