Metadata-Version: 2.1
Name: zen-mechanizm
Version: 1.0.1
Summary: Util to display and export to STL group of objects in ZenCAD
Home-page: https://gitlab.com/hnau_zen/mechanism
Author: Mark Zorikhin
Author-email: hnau256@gmail.com
License: UNKNOWN
Platform: UNKNOWN
Classifier: Programming Language :: Python :: 3
Classifier: License :: OSI Approved :: MIT License
Classifier: Operating System :: OS Independent
Requires-Python: >=3.6
